CHANGES.txt
LICENSE.txt
LICENSE_APACHE.txt
LICENSE_LGPL.txt
MANIFEST.in
README.txt
setup.py
src/p01/__init__.py
src/p01.stemmer.egg-info/PKG-INFO
src/p01.stemmer.egg-info/SOURCES.txt
src/p01.stemmer.egg-info/dependency_links.txt
src/p01.stemmer.egg-info/namespace_packages.txt
src/p01.stemmer.egg-info/not-zip-safe
src/p01.stemmer.egg-info/requires.txt
src/p01.stemmer.egg-info/top_level.txt
src/p01/stemmer/README.txt
src/p01/stemmer/__init__.py
src/p01/stemmer/api.py
src/p01/stemmer/interfaces.py
src/p01/stemmer/performance.py
src/p01/stemmer/stemmer.py
src/p01/stemmer/stopword.py
src/p01/stemmer/tests.py
src/p01/stemmer/data/rslp/step0.pt
src/p01/stemmer/data/rslp/step1.pt
src/p01/stemmer/data/rslp/step2.pt
src/p01/stemmer/data/rslp/step3.pt
src/p01/stemmer/data/rslp/step4.pt
src/p01/stemmer/data/rslp/step5.pt
src/p01/stemmer/data/rslp/step6.pt
src/p01/stemmer/data/stopwords/README
src/p01/stemmer/data/stopwords/danish
src/p01/stemmer/data/stopwords/dutch
src/p01/stemmer/data/stopwords/english
src/p01/stemmer/data/stopwords/finnish
src/p01/stemmer/data/stopwords/french
src/p01/stemmer/data/stopwords/german
src/p01/stemmer/data/stopwords/hungarian
src/p01/stemmer/data/stopwords/italian
src/p01/stemmer/data/stopwords/norwegian
src/p01/stemmer/data/stopwords/portuguese
src/p01/stemmer/data/stopwords/russian
src/p01/stemmer/data/stopwords/spanish
src/p01/stemmer/data/stopwords/swedish
src/p01/stemmer/data/stopwords/turkish